zwx_mcp_test/__init__.py
zwx_mcp_test-0.1.0.dist-info/WHEEL
zwx_mcp_test-0.1.0.dist-info/entry_points.txt
zwx_mcp_test-0.1.0.dist-info/METADATA
zwx_mcp_test-0.1.0.dist-info/RECORD
