Metadata-Version: 2.3
Name: zwx-mcp-test
Version: 0.1.0
Summary: Add your description here
Author: im_fuckMan
Author-email: im_fuckMan <1956043144@qq.com>
Requires-Dist: mcp[cli]>=1.19.0
Requires-Python: >=3.13
